ai/backend/logging/VERSION
ai/backend/logging/__init__.py
ai/backend/logging/abc.py
ai/backend/logging/config.py
ai/backend/logging/exceptions.py
ai/backend/logging/formatter.py
ai/backend/logging/logger.py
ai/backend/logging/otel.py
ai/backend/logging/py.typed
ai/backend/logging/types.py
ai/backend/logging/utils.py
ai/backend/logging/validation_context.py
ai/backend/logging/handler/__init__.py
ai/backend/logging/handler/graylog.py
ai/backend/logging/handler/intrinsic.py
ai/backend/logging/handler/logstash.py
backend_ai_logging-26.1.0.dist-info/METADATA
backend_ai_logging-26.1.0.dist-info/WHEEL
backend_ai_logging-26.1.0.dist-info/namespace_packages.txt
backend_ai_logging-26.1.0.dist-info/top_level.txt
backend_ai_logging-26.1.0.dist-info/RECORD
