Metadata-Version: 2.4
Name: backend.ai-logging
Version: 26.1.0
Summary: Backend.AI Logging Subsystem
Home-page: https://github.com/lablup/backend.ai
Author: Lablup Inc. and contributors
License: MIT
Project-URL: Documentation, https://docs.backend.ai/
Project-URL: Source, https://github.com/lablup/backend.ai
Classifier: Intended Audience :: Developers
Classifier: Operating System :: MacOS :: MacOS X
Classifier: Operating System :: POSIX :: Linux
Classifier: Programming Language :: Python
Classifier: Programming Language :: Python :: 3
Classifier: Environment :: No Input/Output (Daemon)
Classifier: Topic :: Scientific/Engineering
Classifier: Topic :: Software Development
Classifier: Development Status :: 5 - Production/Stable
Classifier: Programming Language :: Python :: 3.13
Classifier: License :: OSI Approved :: MIT License
Requires-Python: >=3.13,<3.14
Requires-Dist: backend.ai-common==26.1.0
Requires-Dist: coloredlogs~=15.0
Requires-Dist: graypy==2.1.0
Requires-Dist: msgpack~=1.1.0
Requires-Dist: opentelemetry-exporter-otlp-proto-grpc~=1.39.0
Requires-Dist: opentelemetry-instrumentation-aiohttp-client~=0.60b0
Requires-Dist: opentelemetry-instrumentation-aiohttp-server~=0.60b0
Requires-Dist: opentelemetry-sdk~=1.39.0
Requires-Dist: psutil~=7.0
Requires-Dist: pydantic[email]~=2.11.3
Requires-Dist: python-json-logger~=3.2.0
Requires-Dist: pyzmq~=26.4
Requires-Dist: trafaret~=2.1
Requires-Dist: types-psutil
Requires-Dist: valkey-glide~=2.2.2
Requires-Dist: yarl~=1.19.0
Dynamic: author
Dynamic: classifier
Dynamic: description
Dynamic: description-content-type
Dynamic: home-page
Dynamic: license
Dynamic: project-url
Dynamic: requires-dist
Dynamic: requires-python
Dynamic: summary
